{"model": "cscg.cypher", "pk": 1185, "fields": {"pub_date": "2024-10-21T21:40:03.113Z", "created": "2024-10-21T21:40:03.113Z", "updated": "2024-10-21T21:40:03.113Z", "name": "Bannissement", "name_en": "Banishing", "effect": "Pendant la journ\u00e9e suivante, chaque fois que l'utilisateur frappe une cr\u00e9ature ou un objet solide, cela g\u00e9n\u00e8re une d\u00e9charge d'\u00e9nergie qui t\u00e9l\u00e9porte la cr\u00e9ature ou l'objet \u00e0 une distance imm\u00e9diate dans une direction al\u00e9atoire (ni vers le haut ni vers le bas). Les actions de la cr\u00e9ature t\u00e9l\u00e9port\u00e9e (y compris la d\u00e9fense) sont entrav\u00e9es \u00e0 son prochain tour (entrav\u00e9es de deux crans si le niveau du cypher est de 5 ou plus).", "hint": "", "table": "", "level": "1d6", "cs_page": "384", "is_manifeste": true, "is_fantastic": false, "is_subtle": false}}