{"model": "cscg.cypher", "pk": 1271, "fields": {"pub_date": "2024-10-21T21:40:04.770Z", "created": "2024-10-21T21:40:04.770Z", "updated": "2024-10-21T21:40:04.770Z", "name": "Poison (\u00c9motion)", "name_en": "Poison (Emotion)", "effect": "La victime ressent une \u00e9motion sp\u00e9cifique pendant une heure. Lancez un d100 pour d\u00e9terminer l'\u00e9motion.", "hint": "=====", "table": "<table class=\"table table-light table-striped table-sm og-dt\">\n  <thead>\n    <tr>\n      <th scope=\"col\" class=\"text-center w-15\">d100</th>\n      <th>\u00c9motion</th>\n    </tr>\n  </thead>\n  <tbody>\n    <tr>\n<td scope=\"col\" class=\"text-center w-15\">01&mdash;20</td>\n      <td>Col\u00e8re. Pr\u00eat \u00e0 attaquer quiconque n'est pas d'accord avec eux. Tr\u00e8s difficile \u00e0 interagir ; toutes ces actions sont entrav\u00e9es de deux \u00e9tapes.</td>\n    </tr>\n    <tr>\n<td scope=\"col\" class=\"text-center w-15\">21&mdash;40</td>\n      <td>Peur. Fuit dans la terreur pendant une minute lorsqu'il est menac\u00e9.</td>\n    </tr>\n    <tr>\n<td scope=\"col\" class=\"text-center w-15\">41&mdash;60</td>\n      <td>D\u00e9sir. Ne peut se concentrer sur aucune activit\u00e9 non sexuelle.</td>\n    </tr>\n    <tr>\n<td scope=\"col\" class=\"text-center w-15\">61&mdash;75</td>\n      <td>Tristesse. Toutes les t\u00e2ches sont entrav\u00e9es.</td>\n    </tr>\n    <tr>\n<td scope=\"col\" class=\"text-center w-15\">76&mdash;85</td>\n      <td>Complaisance. N'a aucune motivation. Toutes les t\u00e2ches sont entrav\u00e9es de deux \u00e9tapes.</td>\n    </tr>\n    <tr>\n<td scope=\"col\" class=\"text-center w-15\">86&mdash;95</td>\n      <td>Joie. Facile \u00e0 interagir de mani\u00e8re agr\u00e9able ; toutes les t\u00e2ches d'interaction agr\u00e9ables sont facilit\u00e9es.</td>\n    </tr>\n    <tr>\n<td scope=\"col\" class=\"text-center w-15\">96&mdash;00</td>\n      <td>Amour. Beaucoup plus facile \u00e0 interagir ; toutes les t\u00e2ches d'interaction sont facilit\u00e9es de deux \u00e9tapes, mais un attachement temporaire est probable.</td>\n    </tr>\n  </tbody>\n</table>", "level": "1d6 + 2", "cs_page": "394", "is_manifeste": true, "is_fantastic": false, "is_subtle": false}}