{"model": "cscg.ability", "pk": 13277, "fields": {"pub_date": "2024-09-18T12:45:55.548Z", "created": "2024-09-18T12:45:55.548Z", "updated": "2024-09-18T12:45:55.548Z", "name": "Avantage par D\u00e9savantage", "name_en": "Advantage to Disadvantage", "stat_cost": "", "stat": "3 points de C\u00e9l\u00e9rit\u00e9", "description": "Avec un certain nombre de mouvements rapides, vous lancez une attaque contre un ennemi arm\u00e9, lui infligeant des d\u00e9g\u00e2ts et le d\u00e9sarmant de sorte que son arme soit maintenant entre vos mains ou \u00e0 10 pieds (3 m) au sol. - \u00e0 vous de choisir. Cette attaque d\u00e9sarmante est entrav\u00e9e. Action.", "cs_page": "109", "tier": "L", "categories": [13]}}