{"model": "cscg.ability", "pk": 13320, "fields": {"pub_date": "2024-09-18T12:45:55.876Z", "created": "2024-09-18T12:45:55.876Z", "updated": "2024-09-18T12:45:55.876Z", "name": "Carnivore sous la Lune", "name_en": "Moon Shape", "stat_cost": "", "stat": "4+ points d'Intellect", "description": "Vous vous transformez en un animal carnivore, comme un loup, un ours ou une autre cr\u00e9ature terrestre, pendant une heure maximum. Si vous essayez de changer pendant la journ\u00e9e lorsque vous n'\u00eates pas profond\u00e9ment sous terre (ou loin de la lumi\u00e8re du jour), vous devez appliquer un niveau d'effort. Dans votre nouvelle forme, vous ajoutez 8 points \u00e0 votre R\u00e9serve de Puissance, gagnez +2 \u00e0 votre Avantage de Puissance, ajoutez 2 points \u00e0 votre Speed \u200b\u200bPool et gagnez +2 \u00e0 votre Speed \u200b\u200bEdge. Revenir \u00e0 votre forme normale est une t\u00e2che de difficult\u00e9 2. Sous forme de b\u00eate, vous \u00eates sujet \u00e0 des crises de rage (d\u00e9clench\u00e9es par l'intrusion du MJ), au cours desquelles vous attaquez toutes les cr\u00e9atures vivantes \u00e0 courte port\u00e9e, et la seule fa\u00e7on de mettre fin \u00e0 la rage est de revenir \u00e0 votre forme normale. Quoi qu'il en soit, une fois revenu \u00e0 votre forme normale, vous subissez une p\u00e9nalit\u00e9 de -1 \u00e0 tous les jets pendant une heure. Si vous n'avez pas tu\u00e9 et mang\u00e9 au moins une cr\u00e9ature substantielle alors que vous \u00e9tiez sous forme de b\u00eate, la p\u00e9nalit\u00e9 passe \u00e0 -2 et affecte tous vos jets du jour suivant. Action pour changer ; action pour revenir en arri\u00e8re.", "cs_page": "164", "tier": "M", "categories": [16]}}