{"model": "cscg.ability", "pk": 13646, "fields": {"pub_date": "2024-09-18T12:45:58.481Z", "created": "2024-09-18T12:45:58.481Z", "updated": "2024-09-18T12:45:58.481Z", "name": "Faisceau de Tonnerre", "name_en": "Thunder Beam", "stat_cost": "", "stat": "2 points de Puissance", "description": "Vous dirigez un faisceau de son concentr\u00e9 sur une cible \u00e0 longue port\u00e9e, lui infligeant 2 points de d\u00e9g\u00e2ts et induisant une onde destructrice r\u00e9sonnante dans son corps. Chaque round apr\u00e8s cette attaque initiale, vous pouvez refaire un jet de vague destructrice pour infliger 1 point de d\u00e9g\u00e2ts suppl\u00e9mentaire \u00e0 la cible. Si vous \u00e9chouez \u00e0 ce jet, la vague destructrice prend fin. Contrairement \u00e0 l'attaque initiale, la vague destructrice ignore l'Armure. Alternativement, vous pouvez cr\u00e9er une r\u00e9sonance destructrice dans une arme physique de m\u00eal\u00e9e pendant une minute ou jusqu'\u00e0 ce que vous la l\u00e2chez. Toutes les attaques effectu\u00e9es avec l'arme cibl\u00e9e infligent 1 point de d\u00e9g\u00e2ts suppl\u00e9mentaire. Action \u00e0 initier.", "cs_page": "191", "tier": "L", "categories": [13]}}