{"model": "cscg.ability", "pk": 13782, "fields": {"pub_date": "2024-09-18T12:45:59.652Z", "created": "2024-09-18T12:45:59.652Z", "updated": "2024-09-18T12:45:59.652Z", "name": "Lancer Illusion", "name_en": "Cast Illusion", "stat_cost": null, "stat": null, "description": "Vous pouvez augmenter la port\u00e9e \u00e0 laquelle vous cr\u00e9ez et maintenez votre illusion \u00e0 port\u00e9e imm\u00e9diate (telles que celles de Illusion mineure) vers n'importe quel endroit \u00e0 courte port\u00e9e que vous pouvez percevoir. Facilitateur.", "cs_page": "118", "tier": "M", "categories": [8]}}