{"model": "cscg.ability", "pk": 13824, "fields": {"pub_date": "2024-09-18T12:46:00.001Z", "created": "2024-09-18T12:46:00.001Z", "updated": "2024-09-18T12:46:00.001Z", "name": "Ma\u00eetre de la d\u00e9fense", "name_en": "Defense Master", "stat_cost": null, "stat": null, "description": "chaque fois que vous r\u00e9ussissez une t\u00e2che de d\u00e9fense rapide, vous pouvez lancer une attaque imm\u00e9diate contre votre ennemi. (Si vous disposez d'Esquive et de R\u00e9ponse, vous pouvez \u00e9changer cette capacit\u00e9 contre Esquive et R\u00e9sistance.) Votre attaque doit \u00eatre du m\u00eame type (arme de m\u00eal\u00e9e, arme \u00e0 distance ou \u00e0 mains nues) que l'attaque contre laquelle vous vous d\u00e9fendez. Si vous ne disposez pas d'un type d'arme appropri\u00e9, vous ne pouvez pas utiliser cette capacit\u00e9. Facilitateur.", "cs_page": "127", "tier": "H", "categories": [10, 13]}}