{"model": "cscg.ability", "pk": 13865, "fields": {"pub_date": "2024-09-18T12:46:00.320Z", "created": "2024-09-18T12:46:00.320Z", "updated": "2024-09-18T12:46:00.320Z", "name": "Montrez-leur le chemin", "name_en": "Show Them the Way", "stat_cost": "", "stat": "6+ points d'Intellect", "description": "Votre pr\u00e9sence submerge une cr\u00e9ature que vous touchez et demandez de vous aider. Essentiellement, si la cr\u00e9ature ne parvient pas \u00e0 se d\u00e9fendre contre votre pr\u00e9sence, vous contr\u00f4lez ses actions pendant dix minutes maximum. La cible doit \u00eatre de niveau 3 ou inf\u00e9rieur. Une fois que vous avez \u00e9tabli le contr\u00f4le, vous le maintenez gr\u00e2ce \u00e0 des instructions verbales. Vous pouvez permettre \u00e0 la cible d'agir librement ou outrepasser le contr\u00f4le au cas par cas. En plus des options normales d'utilisation de l'Effort, vous pouvez choisir d'utiliser l'Effort pour augmenter le niveau maximum de la cible. Ainsi, pour affecter une cible de niveau 5 (deux niveaux au-dessus de la limite normale), vous devez appliquer deux niveaux d'Effort. Lorsque l'effet prend fin, la cr\u00e9ature se souvient vaguement d'avoir fait votre volont\u00e9, mais c'est aussi flou qu'un r\u00eave. Action \u00e0 initier.", "cs_page": "183", "tier": "H", "categories": [3]}}