{"model": "cscg.ability", "pk": 13873, "fields": {"pub_date": "2024-09-18T12:46:00.403Z", "created": "2024-09-18T12:46:00.403Z", "updated": "2024-09-18T12:46:00.403Z", "name": "Multiples Proies", "name_en": "Multiple Quarry", "stat_cost": "", "stat": "6 points d'Intellect", "description": "Cette capacit\u00e9 fonctionne comme la capacit\u00e9 Proie sauf que vous pouvez s\u00e9lectionner jusqu'\u00e0 trois cr\u00e9atures comme proie. Vous devez \u00eatre capable de voir les trois cr\u00e9atures lorsque vous lancez cette capacit\u00e9. Si vous poss\u00e9dez Hunter's Drive, cela s'applique aux trois cr\u00e9atures. Action \u00e0 initier.", "cs_page": "163", "tier": "H", "categories": [8]}}