{"model": "cscg.ability", "pk": 14010, "fields": {"pub_date": "2024-09-18T12:46:01.607Z", "created": "2024-09-18T12:46:01.607Z", "updated": "2024-09-18T12:46:01.607Z", "name": "Recueillir des renseignements", "name_en": "Gather Intelligence", "stat_cost": "", "stat": "2 points d'Intellect", "description": "Lorsque vous \u00eates dans un groupe de personnes (une caravane, un palais, un village, une ville, etc.), vous pouvez poser des questions sur n'importe quel sujet de votre choix et repartir avec des informations utiles. Vous pouvez poser une question sp\u00e9cifique ou simplement obtenir des faits g\u00e9n\u00e9raux. Vous aurez \u00e9galement une bonne id\u00e9e de la disposition g\u00e9n\u00e9rale du lieu concern\u00e9, noterez la pr\u00e9sence de tous les sites majeurs et remarquerez peut-\u00eatre m\u00eame des d\u00e9tails obscurs. Par exemple, non seulement vous d\u00e9couvrez si quelqu'un dans le palais a vu le gar\u00e7on disparu, mais vous obtenez \u00e9galement une connaissance pratique de l'agencement du palais lui-m\u00eame, notez toutes les entr\u00e9es et celles qui sont utilis\u00e9es plus souvent que d'autres, et prenez remarquez que tout le monde semble \u00e9viter le puits dans la cour est pour une raison quelconque. Action \u00e0 initier, environ une heure \u00e0 r\u00e9aliser.", "cs_page": "144", "tier": "L", "categories": [7]}}