{"model": "cscg.ability", "pk": 14078, "fields": {"pub_date": "2024-09-18T12:46:02.176Z", "created": "2024-09-18T12:46:02.176Z", "updated": "2024-09-18T12:46:02.176Z", "name": "Science du Sommeil", "name_en": "Oneirochemy", "stat_cost": null, "stat": null, "description": "Vous \u00eates entra\u00een\u00e9 aux t\u00e2ches li\u00e9es au sommeil et au m\u00e9lange d'\u00e9lixirs naturels pour aider les cr\u00e9atures \u00e0 s'endormir. Facilitateur.", "cs_page": "167", "tier": "L", "categories": [15]}}