{"model": "cscg.ability", "pk": 14102, "fields": {"pub_date": "2024-09-18T12:46:02.329Z", "created": "2024-09-18T12:46:02.329Z", "updated": "2024-09-18T12:46:02.329Z", "name": "Soif de sang", "name_en": "Bloodlust", "stat_cost": "", "stat": "3 points de Puissance", "description": "Si vous \u00e9liminez un ennemi, vous pouvez vous d\u00e9placer sur une courte distance, mais seulement si vous vous dirigez vers un autre ennemi. Vous n'avez pas besoin de d\u00e9penser des points tant que vous ne savez pas que le premier ennemi est \u00e0 terre. Facilitateur.", "cs_page": "115", "tier": "L", "categories": [13]}}