{"model": "cscg.ability", "pk": 14165, "fields": {"pub_date": "2024-09-18T12:46:02.872Z", "created": "2024-09-18T12:46:02.872Z", "updated": "2024-09-18T12:46:02.872Z", "name": "Toucher lumineux", "name_en": "Illuminating Touch", "stat_cost": "", "stat": "1 point d'Intellect", "description": "Vous touchez un objet, et cet objet \u00e9met de la lumi\u00e8re pour tout \u00e9clairer \u00e0 courte port\u00e9e. La lumi\u00e8re reste jusqu'\u00e0 ce que vous utilisiez une action pour toucher \u00e0 nouveau l'objet, ou jusqu'\u00e0 ce que vous ayez \u00e9clair\u00e9 plus d'objets que vous n'avez de niveaux, auquel cas les objets les plus anciens que vous avez \u00e9clair\u00e9s s'assombrissent en premier. Action.", "cs_page": "150", "tier": "L", "categories": [6]}}