{"model": "cscg.ability", "pk": 14187, "fields": {"pub_date": "2024-09-18T12:46:03.075Z", "created": "2024-09-18T12:46:03.075Z", "updated": "2024-09-18T12:46:03.075Z", "name": "Tremblement de r\u00e9sonance", "name_en": "Resonant Quake", "stat_cost": "", "stat": "7 points d'Intellect", "description": "Vous pouvez impr\u00e9gner le sol sous vous d'une vibration sp\u00e9ciale g\u00e9n\u00e9r\u00e9e par votre c\u0153ur. Cela cr\u00e9e un petit s\u00e9isme dont vous pouvez s\u00e9lectionner l'\u00e9picentre sur une tr\u00e8s longue distance. Toute personne se trouvant \u00e0 courte port\u00e9e de l'\u00e9picentre est sujette \u00e0 8 points de d\u00e9g\u00e2ts (en tremblant et en \u00e9tant frapp\u00e9e par des objets qui tombent, des murs qui s'effondrent, etc.). Cependant, vous restez vous-m\u00eame h\u00e9b\u00e9t\u00e9 pendant un tour, pendant lequel toutes vos t\u00e2ches sont entrav\u00e9es. Si vous disposez de la capacit\u00e9 D\u00e9placer les montagnes, les deux capacit\u00e9s co\u00fbtent 3 points d'Intellect de moins \u00e0 utiliser. Action.", "cs_page": "177", "tier": "H", "categories": [13]}}