{"model": "cscg.focus", "pk": 724, "fields": {"pub_date": "2024-09-20T15:56:29.973Z", "created": "2024-09-20T15:56:29.973Z", "updated": "2024-09-20T15:56:29.973Z", "name": "S'Envole Gr\u00e2ce \u00e0 ses Ailes", "name_en": "Soars On Amazing Wings", "description": "De nombreux super-h\u00e9ros peuvent voler et certains ont m\u00eame des ailes. Vous pouvez utiliser vos\n      ailes pour vous d\u00e9placer, attaquer et vous d\u00e9fendre.", "abilities_tier1": 1499, "abilities_tier2": 1500, "abilities_tier3": 1501, "abilities_tier4": 1502, "abilities_tier5": 1503, "abilities_tier6": 1504}}