{"model": "cscg.descriptor", "pk": 1111, "fields": {"pub_date": "2024-09-25T20:15:31.436Z", "created": "2024-09-25T20:15:31.436Z", "updated": "2024-09-25T20:15:31.436Z", "name": "L\u00e2che", "name_en": "", "description": "Le courage vous fait d\u00e9faut \u00e0 chaque instant. Vous\n      manquez de volont\u00e9 et de d\u00e9termination pour tenir bon face au danger. La peur vous ronge le\n      c\u0153ur, ronge votre esprit, vous conduit \u00e0 la distraction jusqu'\u00e0 ce que vous ne puissiez plus\n      la supporter. La plupart du temps, vous reculez devant les confrontations. Vous fuyez les\n      menaces et h\u00e9sitez face \u00e0 des d\u00e9cisions difficiles.Pourtant, malgr\u00e9 toute la peur qui vous\n      hante et peut-\u00eatre vous fait honte, votre nature l\u00e2che se r\u00e9v\u00e8le \u00eatre un alli\u00e9 utile de temps\n      en temps. \u00c9couter vos peurs vous a aid\u00e9 \u00e0 \u00e9chapper au danger et \u00e0 \u00e9viter de prendre des\n      risques inutiles. D'autres ont peut-\u00eatre souffert \u00e0 votre place, et vous \u00eates peut-\u00eatre le\n      premier \u00e0 l'admettre, mais secr\u00e8tement, vous ressentez un intense soulagement d'avoir \u00e9vit\u00e9 un\n      destin impensable et terrible.{{< hint info >}}Des descripteurs comme L\u00e2che, Cruel et\n      D\u00e9shonorant pourraient ne pas convenir \u00e0 tous les groupes. Ce sont des traits de caract\u00e8re\n      attribu\u00e9s plut\u00f4t pour les opposants des PJs et certaines personnes souhaitent que leurs PJ\n      soient enti\u00e8rement h\u00e9ro\u00efques. Mais d'autres ne voient pas d'inconv\u00e9nient \u00e0 ce qu'un peu de\n      grisaille morale vienne s'ajouter \u00e0 ce m\u00e9lange. D'autres encore voient des choses comme L\u00e2che\n      et Cruel comme des traits \u00e0 surmonter \u00e0 mesure que leurs personnages se d\u00e9veloppent (ce qui\n      leur vaut probablement des descripteurs diff\u00e9rents).{{< /hint >}}", "cs_page": "", "characteristics": [2014, 2015, 2016, 2017, 2018, 2019, 2020], "initial_links": [3033, 3034, 3035, 3036]}}